notifs/__init__.py
notifs/core.py
notifs-0.2.0.dist-info/METADATA
notifs-0.2.0.dist-info/WHEEL
notifs-0.2.0.dist-info/top_level.txt
notifs-0.2.0.dist-info/RECORD
