Metadata-Version: 2.1
Name: notifs
Version: 0.2.0
Summary: Customizable notification system for terminal output
Author: doot
Author-email: doot@waifu.club
